pylan/__init__.py
pylan/granularity.py
pylan/item.py
pylan/result.py
pylan/schedule.py
pylan/projections/__init__.py
pylan/projections/add.py
pylan/projections/divide.py
pylan/projections/multiply.py
pylan/projections/replace.py
pylan/projections/subtract.py
pylan_lib-0.3.0.dist-info/METADATA
pylan_lib-0.3.0.dist-info/WHEEL
pylan_lib-0.3.0.dist-info/top_level.txt
pylan_lib-0.3.0.dist-info/RECORD
