Metadata-Version: 2.4
Name: pylan-lib
Version: 0.3.0
Summary: Python library that simulates the combined impact of recurring events.
Home-page: https://github.com/TimoKats/pylan
Author: Timo Kats
Author-email: hello@timokats.xyz
License: BSD
Keywords: timeseries,simulation,planning
Requires-Dist: python-dateutil
Requires-Dist: cron-converter
Dynamic: author
Dynamic: author-email
Dynamic: description
Dynamic: description-content-type
Dynamic: home-page
Dynamic: keywords
Dynamic: license
Dynamic: requires-dist
Dynamic: summary
